{
  "Ads": [
    {
      "more_app"                  : "1",
      "select_main_ads"           : "ADMOB",
      "select_backup_ads"         : "ADMOB",

      "main_ads_banner"           : "ca-app-pub-6673205636597113/9882073224",
      "main_ads_intertitial"      : "ca-app-pub-6673205636597113/4434505110",
      "main_ads_native"           : "ca-app-pub-6673205636597113/9423942069",

      "open_ads"                  : "ca-app-pub-6673205636597113/3172947228",

      "backup_ads_banner"         : "null",
      "backup_ads_intertitial"    : "null",
      "backup_ads_native"         : "null",
      
      "initialize_sdk"            : "null",
      "initialize_sdk_backup_ads" : "null",

      "interval_intertitial"      : 5,

      "high_paying_keyword_1"     : "",
      "high_paying_keyword_2"     : "",
      "high_paying_keyword_3"     : "",
      "high_paying_keyword_4"     : "",
      "high_paying_keyword_5"     : "",

      "status_app": "0",
      "link_redirect": "https://"
      }
  ]
}